tree_sitter_cleancopy/__init__.py
tree_sitter_cleancopy/__init__.pyi
tree_sitter_cleancopy/_binding.pyd
tree_sitter_cleancopy/binding.c
tree_sitter_cleancopy/py.typed
tree_sitter_cleancopy-0.0.18.dist-info/LICENSE
tree_sitter_cleancopy-0.0.18.dist-info/METADATA
tree_sitter_cleancopy-0.0.18.dist-info/WHEEL
tree_sitter_cleancopy-0.0.18.dist-info/top_level.txt
tree_sitter_cleancopy-0.0.18.dist-info/RECORD
